Metadata-Version: 2.1
Name: uszipstats
Version: 0.2
Summary: sample package
Home-page: https://github.com/vrathi101/uszipstats.git
Download-URL: https://github.com/vrathi101/uszipstats/archive/refs/tags/v_02.tar.gz
Author: VEDANT RATHI
Author-email: vedrathi10@gmail.com
License: MIT
Keywords: DATA,FUNCTIONS
Classifier: Development Status :: 3 - Alpha
Classifier: Intended Audience :: Developers
Classifier: Topic :: Software Development :: Build Tools
Classifier: License :: OSI Approved :: MIT License
Classifier: Programming Language :: Python :: 3.7
Classifier: Programming Language :: Python :: 3.8
Classifier: Programming Language :: Python :: 3.8
Classifier: Programming Language :: Python :: 3.9
License-File: LICENSE.txt
